tongsmath/__init__.py
tongsmath/temp.py
tongsmath/Function/__init__.py
tongsmath/Function/func.py
tongsmath/Primenumber/DPN.py
tongsmath/Primenumber/__init__.py
tongsmath/Simplify/__init__.py
tongsmath/Simplify/sim2ndrt.py
tongsmath/Statistics/__init__.py
tongsmath/Statistics/data.py
tongsmath-1.3.15.dist-info/LICENSE.txt
tongsmath-1.3.15.dist-info/METADATA
tongsmath-1.3.15.dist-info/WHEEL
tongsmath-1.3.15.dist-info/top_level.txt
tongsmath-1.3.15.dist-info/RECORD
