Metadata-Version: 2.1
Name: tongsmath
Version: 1.3.15
Summary: tong's math library
Home-page: https://github.com/
Author: Tong
Author-email: 3231690635@qq.com
License: UNKNOWN
Platform: UNKNOWN
Classifier: Programming Language :: Python :: 3
Classifier: License :: OSI Approved :: MIT License
Classifier: Operating System :: OS Independent
License-File: LICENSE.txt
